README.txt
setup.py
collective/__init__.py
collective.portlet.fblikebox.egg-info/PKG-INFO
collective.portlet.fblikebox.egg-info/SOURCES.txt
collective.portlet.fblikebox.egg-info/dependency_links.txt
collective.portlet.fblikebox.egg-info/entry_points.txt
collective.portlet.fblikebox.egg-info/namespace_packages.txt
collective.portlet.fblikebox.egg-info/not-zip-safe
collective.portlet.fblikebox.egg-info/requires.txt
collective.portlet.fblikebox.egg-info/top_level.txt
collective/portlet/__init__.py
collective/portlet/fblikebox/__init__.py
collective/portlet/fblikebox/configure.zcml
collective/portlet/fblikebox/likeboxportlet.pt
collective/portlet/fblikebox/likeboxportlet.py
collective/portlet/fblikebox/version.txt
collective/portlet/fblikebox/profiles/default/metadata.xml
collective/portlet/fblikebox/profiles/default/portlets.xml
collective/portlet/fblikebox/tests/__init__.py
collective/portlet/fblikebox/tests/base.py
collective/portlet/fblikebox/tests/test_portlet.py
docs/HISTORY.txt
docs/INSTALL.txt
docs/LICENSE.GPL
docs/LICENSE.txt