Metadata-Version: 1.0
Name: collective.portlet.fblikebox
Version: 1.0
Summary: Facebook Like-Box Portlet
Home-page: http://svn.plone.org/svn/collective/collective.portlet.fblikebox
Author: Steve McMahon
Author-email: steve@dcn.org
License: GPL2
Keywords: Facebook Plone Portlet
Platform: UNKNOWN
Classifier: Framework :: Plone
Classifier: Programming Language :: Python
